groc/__init__.py
groc/__main__.py
groc/cli.py
groc/db.py
groc/exceptions.py
groc/models.py
groc/utils.py
groc/version.py
groc-0.1.2.dist-info/LICENSE
groc-0.1.2.dist-info/METADATA
groc-0.1.2.dist-info/WHEEL
groc-0.1.2.dist-info/entry_points.txt
groc-0.1.2.dist-info/top_level.txt
groc-0.1.2.dist-info/RECORD
