Metadata-Version: 2.1
Name: groc
Version: 0.1.2
Summary: Streamline your purchase history
Home-page: https://github.com/sjbitcode/groc
Author: Sangeeta Jadoonanan
Author-email: sjbitcode@gmail.com
License: MIT
Platform: UNKNOWN
Classifier: License :: OSI Approved :: MIT License
Classifier: Programming Language :: Python :: 3
Classifier: Programming Language :: Python :: 3.7
